README.md
setup.cfg
setup.py
TOPSIS_SIMRANPREET_101803175/topsis.py
TOPSIS_SIMRANPREET_101803175.egg-info/PKG-INFO
TOPSIS_SIMRANPREET_101803175.egg-info/SOURCES.txt
TOPSIS_SIMRANPREET_101803175.egg-info/dependency_links.txt
TOPSIS_SIMRANPREET_101803175.egg-info/entry_points.txt
TOPSIS_SIMRANPREET_101803175.egg-info/requires.txt
TOPSIS_SIMRANPREET_101803175.egg-info/top_level.txt