Metadata-Version: 2.1
Name: TOPSIS-SIMRANPREET-101803175
Version: 1.1.1
Summary: A Python package for topsis analysis.
Home-page: UNKNOWN
Author: SIMRANPREET SINGH
Author-email: ssingh4_be18@thapar.edu
License: MIT
Platform: UNKNOWN
Classifier: License :: OSI Approved :: MIT License
Classifier: Programming Language :: Python :: 3
Classifier: Programming Language :: Python :: 3.7
